Renpy_Tools/Help_Cn.py
Renpy_Tools/__init__.py
Renpy_Tools/__main__.py
Renpy_Tools/exc_tran.py
Renpy_Tools/get_text.py
Renpy_Tools/get_tran_inf.py
Renpy_Tools/repl_tran.py
Renpy_Tools-0.0.3.dist-info/LICENSE
Renpy_Tools-0.0.3.dist-info/METADATA
Renpy_Tools-0.0.3.dist-info/WHEEL
Renpy_Tools-0.0.3.dist-info/top_level.txt
Renpy_Tools-0.0.3.dist-info/RECORD
