Metadata-Version: 2.1
Name: Renpy-Tools
Version: 0.0.3
Summary: 操作Renpy的文件
Home-page: https://github.com/clodlingxi
Author: ClodLingxi
Author-email: clodlingxi@qq.com
License: UNKNOWN
Platform: UNKNOWN
Classifier: Programming Language :: Python :: 3
Classifier: License :: OSI Approved :: MIT License
Classifier: Operating System :: OS Independent
